podfeed/__init__.py
podfeed/dateutils.py
podfeed/parser.py
podfeed/playlists.py
podfeed-1.0.1.dist-info/LICENSE.md
podfeed-1.0.1.dist-info/METADATA
podfeed-1.0.1.dist-info/WHEEL
podfeed-1.0.1.dist-info/top_level.txt
podfeed-1.0.1.dist-info/RECORD
