Metadata-Version: 2.1
Name: podfeed
Version: 1.0.1
Summary: A simple podcast feed parser
Home-page: https://github.com/mmazzocchi/podfeed
Author: Max Mazzocchi
Author-email: maxwell.mazzocchi@gmail.com
License: UNKNOWN
Keywords: podcast RSS feed parser
Platform: UNKNOWN
Classifier: Development Status :: 4 - Beta
Classifier: Programming Language :: Python :: 3
Classifier: License :: OSI Approved :: MIT License
Classifier: Operating System :: OS Independent
Classifier: Intended Audience :: Developers
Classifier: Topic :: Multimedia :: Sound/Audio
Requires-Python: >=3
Requires-Dist: feedparser
